{
  "CreateEvent": {
    "tags": [
      "Event"
    ],
    "description": "Creates an event",
    "operationId": "createEvent",
    "security": [
      {
        "Authorization": []
      }
    ],
    "parameters": [
      {
        "in": "body",
        "name": "body",
        "description": "Event object that needs to be added to the database",
        "required": true,
        "schema": {
          "$ref": "../definitions/event.json#/Event"
        }
      }
    ],
    "responses": {
      "200": {
        "description": "Success",
        "schema": {
          "$ref": "../definitions/event.json#/CreateEventResponse"
        }
      },
      "500": {
        "description": "Error",
        "schema": {
          "$ref": "../definitions/error.json#/ErrorResponse"
        }
      }
    }
  },
  "UpdateEvent": {
    "tags": [
      "Event"
    ],
    "description": "Updates a event",
    "operationId": "updateEvent",
    "security": [
      {
        "Authorization": []
      }
    ],
    "parameters": [
      {
        "in": "body",
        "name": "body",
        "description": "Updates the event passed in the body",
        "required": true,
        "schema": {
          "$ref": "../definitions/event.json#/UpdateEvent"
        }
      }
    ],
    "responses": {
      "200": {
        "description": "Success",
        "schema": {
          "$ref": "../definitions/generic.json#/UpdateResponse"
        }
      },
      "404": {
        "description": "Event not found",
        "schema": {
          "$ref": "../definitions/error.json#/ErrorResponse"
        }
      },
      "500": {
        "description": "Error",
        "schema": {
          "$ref": "../definitions/error.json#/ErrorResponse"
        }
      }
    }
  }
}